README.md
setup.py
KubeGrade.egg-info/PKG-INFO
KubeGrade.egg-info/SOURCES.txt
KubeGrade.egg-info/dependency_links.txt
KubeGrade.egg-info/requires.txt
KubeGrade.egg-info/top_level.txt
KubeGrade.egg-info/zip-safe
validator/__init__.py
validator/base.py
validator/config.py
validator/container.py
validator/controller.py
validator/messages.py
validator/namespace.py
validator/pod.py
validator/resource.py
validator/validator.py
validator/controllers/__init__.py
validator/controllers/cron_job.py
validator/controllers/daemon_set.py
validator/controllers/deployment.py
validator/controllers/job.py
validator/controllers/stateful_set.py
validator/kube/__init__.py
validator/kube/resource.py